doc/__init__.py
doc/conf.py
doc/rst_builders/__init__.py
doc/rst_builders/generate_components.py
doc/rst_builders/generate_fragments.py
doc/rst_builders/generate_interfaces.py
epyk/__init__.py
epyk/_version.py
epyk/conf/__init__.py
epyk/conf/global_settings.py
epyk/core/Page.py
epyk/core/__init__.py
epyk/core/auth/__init__.py
epyk/core/cli/__init__.py
epyk/core/cli/cli_export.py
epyk/core/cli/cli_npm.py
epyk/core/cli/cli_project.py
epyk/core/cli/utils.py
epyk/core/css/Classes.py
epyk/core/css/Colors.py
epyk/core/css/Defaults.py
epyk/core/css/FontFamily.py
epyk/core/css/Icons.py
epyk/core/css/Properties.py
epyk/core/css/Selector.py
epyk/core/css/__init__.py
epyk/core/css/catalogs/Catalog.py
epyk/core/css/catalogs/CatalogButton.py
epyk/core/css/catalogs/CatalogChart.py
epyk/core/css/catalogs/CatalogDiv.py
epyk/core/css/catalogs/CatalogIcons.py
epyk/core/css/catalogs/CatalogImg.py
epyk/core/css/catalogs/CatalogInput.py
epyk/core/css/catalogs/CatalogLayout.py
epyk/core/css/catalogs/CatalogLink.py
epyk/core/css/catalogs/CatalogList.py
epyk/core/css/catalogs/CatalogMedia.py
epyk/core/css/catalogs/CatalogPopup.py
epyk/core/css/catalogs/CatalogRadio.py
epyk/core/css/catalogs/CatalogSelect.py
epyk/core/css/catalogs/CatalogStd.py
epyk/core/css/catalogs/CatalogTable.py
epyk/core/css/catalogs/CatalogText.py
epyk/core/css/catalogs/CatalogTree.py
epyk/core/css/catalogs/__init__.py
epyk/core/css/native/common-vars-dark.css
epyk/core/css/native/common-vars.css
epyk/core/css/native/contents-table.css
epyk/core/css/native/html-base.css
epyk/core/css/native/html-button.css
epyk/core/css/native/html-comments.css
epyk/core/css/native/html-drawer.css
epyk/core/css/native/html-filters.css
epyk/core/css/native/html-footer.css
epyk/core/css/native/html-helper.css
epyk/core/css/native/html-icons.css
epyk/core/css/native/html-input-date.css
epyk/core/css/native/html-input-range.css
epyk/core/css/native/html-input-time.css
epyk/core/css/native/html-input.css
epyk-1.12.31.dist-info/LICENSE
epyk-1.12.31.dist-info/METADATA
epyk-1.12.31.dist-info/WHEEL
epyk-1.12.31.dist-info/entry_points.txt
epyk-1.12.31.dist-info/top_level.txt
epyk-1.12.31.dist-info/RECORD
