Metadata-Version: 2.1
Name: epyk
Version: 1.12.31
Summary: A simple way to create rich interactive websites and dashboards compatible with modern web frameworks
Home-page: https://github.com/epykure/epyk-ui
Author: epykure
Author-email: smith.pyotr@gmail.com
Project-URL: Documentation, http://www.epyk.io
Project-URL: Code, https://github.com/epykure/epyk-ui
Project-URL: Issue tracker, https://github.com/epykure/epyk-ui/issues
Classifier: Programming Language :: Python :: 3
Classifier: License :: OSI Approved :: GNU General Public License (GPL)
Classifier: Operating System :: OS Independent
Requires-Python: >=3.5
License-File: LICENSE
